prompted/__init__.py
prompted/create.py
prompted/mcp.py
prompted/mcp_utils.py
prompted/py.typed
prompted/agents/__init__.py
prompted/agents/agent.py
prompted/agents/agent_tool.py
prompted/agents/agent_types.py
prompted/common/__init__.py
prompted/common/cache.py
prompted/common/logger.py
prompted/types/__init__.py
prompted/types/a2a.py
prompted/types/chat_completions.py
prompted/types/chat_completions_params.py
prompted/types/instructor.py
prompted/types/mcp.py
prompted/utils/__init__.py
prompted/utils/converters.py
prompted/utils/formatting.py
prompted/utils/identification.py
prompted/utils/mock.py
prompted/utils/streaming.py
prompted-0.0.12.dist-info/METADATA
prompted-0.0.12.dist-info/WHEEL
prompted-0.0.12.dist-info/licenses/LICENSE
prompted-0.0.12.dist-info/RECORD
