Metadata-Version: 2.4
Name: prompted
Version: 0.0.12
Summary: Simple types & utilities built for the OpenAI Chat Completions API specification.
Author-email: Hammad Saeed <hvmmad@gmail.com>
License:                                  Apache License
License-File: LICENSE
Requires-Python: >=3.10
Requires-Dist: cachetools>=5.5.1
Requires-Dist: docstring-parser>=0.16
Requires-Dist: pydantic>=2.10.6
Requires-Dist: rich>=13.9.4
Requires-Dist: typing-inspect>=0.9.0
Provides-Extra: a2a
Requires-Dist: fasta2a; extra == 'a2a'
Provides-Extra: all
Requires-Dist: fasta2a; extra == 'all'
Requires-Dist: instructor>=1.8.2; extra == 'all'
Requires-Dist: litellm>=1.61.3; extra == 'all'
Requires-Dist: mcp>=1.9.0; extra == 'all'
Provides-Extra: create
Requires-Dist: instructor>=1.8.2; extra == 'create'
Requires-Dist: litellm>=1.61.3; extra == 'create'
Provides-Extra: mcp
Requires-Dist: mcp>=1.9.0; extra == 'mcp'
Provides-Extra: samples
Requires-Dist: ipykernel; extra == 'samples'
Requires-Dist: ipython; extra == 'samples'
Requires-Dist: typer; extra == 'samples'
